{"./":{"url":"./","title":"Node.js","keywords":"","body":"Node.js Node.js 是一个免费、开源、跨平台的 JavaScript 运行时环境。 它让开发人员能够创建服务器、 Web 应用、命令行工具和脚本。 "},"docs/安装 Node.js.html":{"url":"docs/安装 Node.js.html","title":"安装 Node.js","keywords":"","body":"安装 Node.js 要了解更多选择，在 Node.js 官方网站上有适用于各种系统的 安装步骤 。 "},"docs/缓冲区.html":{"url":"docs/缓冲区.html","title":"缓冲区","keywords":"","body":"缓冲区 执行下面的代码，创建指定字节大小的缓冲区。 let buffer = Buffer.alloc(10); console.log(buffer); 执行下面的代码，创建指定字节大小的缓冲区，但缓冲区中可能存在旧的数据。 let buffer = Buffer.allocUnsafe(100); console.log(buffer); 执行下面的代码，实现缓冲区与字符串的转换。 let buffer = Buffer.from('Hello Node.js!'); console.log(buffer); console.log(buffer.toString()); 也可以创建一个包含数组的缓冲区。 let buffer = Buffer.from([233, 666, 100]); console.log(buffer); "},"docs/文件系统.html":{"url":"docs/文件系统.html","title":"文件系统","keywords":"","body":"文件系统 执行下面的代码，创建指定的文件并写入内容。 "}}